dwatch/__init__.py
dwatch/_version.py
dwatch/cli.py
dwatch/config.py
dwatch/mail.py
dwatch/monitor.py
dwatch/render.py
dwatch/report_template.jinja.html
dwatch/report_template.jinja.txt
dwatch-0.4.1.dist-info/licenses/LICENSE
dwatch-0.4.1.dist-info/METADATA
dwatch-0.4.1.dist-info/WHEEL
dwatch-0.4.1.dist-info/entry_points.txt
dwatch-0.4.1.dist-info/top_level.txt
dwatch-0.4.1.dist-info/RECORD
