Metadata-Version: 2.4
Name: dwatch
Version: 0.4.1
Summary: A tool to watch command output for differences and send notifications.
Author-email: Ingo Meyer <i.meyer@fz-juelich.de>
Maintainer-email: Ingo Meyer <i.meyer@fz-juelich.de>
License: Copyright 2022 Forschungszentrum Jülich GmbH
Project-URL: Homepage, https://github.com/IngoMeyer441/dwatch
Keywords: administration,monitoring
Classifier: Development Status :: 5 - Production/Stable
Classifier: Environment :: Console
Classifier: Intended Audience :: System Administrators
Classifier: License :: OSI Approved :: MIT License
Classifier: Natural Language :: English
Classifier: Operating System :: POSIX :: Linux
Classifier: Programming Language :: Python
Classifier: Programming Language :: Python :: 3
Classifier: Programming Language :: Python :: 3 :: Only
Classifier: Programming Language :: Python :: 3.9
Classifier: Programming Language :: Python :: 3.10
Classifier: Programming Language :: Python :: 3.11
Classifier: Programming Language :: Python :: 3.12
Classifier: Programming Language :: Python :: 3.13
Classifier: Programming Language :: Python :: 3.14
Classifier: Topic :: System :: Systems Administration
Classifier: Topic :: Utilities
Requires-Python: >=3.9
License-File: LICENSE
Requires-Dist: filelock
Requires-Dist: Jinja2
Requires-Dist: yacl[colored_exceptions]
Dynamic: license-file
